[
    {
        "requestId": "0EE65154B3F80C4E697592B510D06146",
        "loaderId": "0EE65154B3F80C4E697592B510D06146",
        "documentURL": "https://www.maersk.com/",
        "request": {
            "url": "https://www.maersk.com/",
            "method": "GET",
            "headers": {
                "Upgrade-Insecure-Requests": "1",
                "User-Agent": "Mozilla/5.0 AppleWebKit/537.36 (KHTML, like Gecko; compatible; Googlebot/2.1; +http://www.google.com/bot.html) Chrome/115.0.0.0 Safari/537.36",
                "sec-ch-ua": "",
                "sec-ch-ua-mobile": "?0",
                "sec-ch-ua-platform": "\"\""
            },
            "mixedContentType": "none",
            "initialPriority": "VeryHigh",
            "referrerPolicy": "strict-origin-when-cross-origin",
            "isSameSite": true
        },
        "timestamp": 8960.123718,
        "wallTime": 1694246820.696077,
        "initiator": {
            "type": "other"
        },
        "redirectHasExtraInfo": false,
        "type": "Document",
        "frameId": "8B1E04AB0B2BE97F280C1123D2C0D4BD",
        "hasUserGesture": false,
        "cookies": {
            "cookies": []
        }
    }
]