[
    {
        "requestId": "3FCFAB82FC621785903EC9ADD02449D3",
        "loaderId": "3FCFAB82FC621785903EC9ADD02449D3",
        "documentURL": "https://www.ups.com/",
        "request": {
            "url": "https://www.ups.com/",
            "method": "GET",
            "headers": {
                "Upgrade-Insecure-Requests": "1",
                "User-Agent": "Mozilla/5.0 AppleWebKit/537.36 (KHTML, like Gecko; compatible; Googlebot/2.1; +http://www.google.com/bot.html) Chrome/115.0.0.0 Safari/537.36",
                "sec-ch-ua": "",
                "sec-ch-ua-mobile": "?0",
                "sec-ch-ua-platform": "\"\""
            },
            "mixedContentType": "none",
            "initialPriority": "VeryHigh",
            "referrerPolicy": "strict-origin-when-cross-origin",
            "isSameSite": true
        },
        "timestamp": 16835.792454,
        "wallTime": 1694254696.364388,
        "initiator": {
            "type": "other"
        },
        "redirectHasExtraInfo": false,
        "type": "Document",
        "frameId": "C7198A2B6A941ACF50E8B6012B016017",
        "hasUserGesture": false,
        "cookies": {
            "cookies": []
        }
    }
]