{
    "website url": "https://www.mobile.de/",
    "hostname": "www.mobile.de",
    "subject": {
        "jurisdictionCountryName": "DE",
        "jurisdictionStateOrProvinceName": "Brandenburg",
        "jurisdictionLocalityName": "Potsdam",
        "businessCategory": "Private Organization",
        "serialNumber": "HRB 18517",
        "countryName": "DE",
        "stateOrProvinceName": "Brandenburg",
        "localityName": "Kleinmachnow",
        "organizationName": "mobile.de GmbH",
        "commonName": "www.mobile.de"
    },
    "issuer": {
        "countryName": "US",
        "organizationName": "DigiCert Inc",
        "organizationalUnitName": "www.digicert.com",
        "commonName": "DigiCert SHA2 Extended Validation Server CA"
    },
    "version": 3,
    "not_before": "Jul 26 00:00:00 2023 GMT",
    "not_after": "Mar 14 23:59:59 2024 GMT",
    "valid_period": 232,
    "serial_number": "0FE4418D99EA14E83BCBC77B6A142D97",
    "signature_algo": "sha256WithRSAEncryption",
    "protocol_version": "TLSv1.3",
    "alternate subject name": [
        [
            "DNS",
            "www.mobile.de"
        ],
        [
            "DNS",
            "achat-occasion.automobile.fr"
        ],
        [
            "DNS",
            "admin.automobile.fr"
        ],
        [
            "DNS",
            "admin.mobile.de"
        ],
        [
            "DNS",
            "admin2.mobile.de"
        ],
        [
            "DNS",
            "adstream.mobile.de"
        ],
        [
            "DNS",
            "ap-recherche.automobile.fr"
        ],
        [
            "DNS",
            "apptest.mobile.de"
        ],
        [
            "DNS",
            "archiv.mobile.de"
        ],
        [
            "DNS",
            "auto-verkaufen.mobile.de"
        ],
        [
            "DNS",
            "autoact.mobile.de"
        ],
        [
            "DNS",
            "fb.mobile.de"
        ],
        [
            "DNS",
            "ftp.automobile.fr"
        ],
        [
            "DNS",
            "gb-suche.mobile.de"
        ],
        [
            "DNS",
            "haendler.mobile.de"
        ],
        [
            "DNS",
            "handel.mobile.de"
        ],
        [
            "DNS",
            "home.automobile.fr"
        ],
        [
            "DNS",
            "home.mobile.de"
        ],
        [
            "DNS",
            "id.handel.mobile.de"
        ],
        [
            "DNS",
            "id.mobile.de"
        ],
        [
            "DNS",
            "login.automobile.fr"
        ],
        [
            "DNS",
            "login.mobile.de"
        ],
        [
            "DNS",
            "m.automobile.fr"
        ],
        [
            "DNS",
            "m.mobile.de"
        ],
        [
            "DNS",
            "m2.mobile.de"
        ],
        [
            "DNS",
            "mobile.de"
        ],
        [
            "DNS",
            "opencms.mobile.de"
        ],
        [
            "DNS",
            "p.mobile.de"
        ],
        [
            "DNS",
            "services.mobile.de"
        ],
        [
            "DNS",
            "suchen.mobile.de"
        ],
        [
            "DNS",
            "ticker.mobile.de"
        ],
        [
            "DNS",
            "www.automobile.fr"
        ]
    ]
}