[
    {
        "requestId": "50846128993302ADE41620A795EA96C2",
        "loaderId": "50846128993302ADE41620A795EA96C2",
        "documentURL": "https://frontier.com/",
        "request": {
            "url": "https://frontier.com/",
            "method": "GET",
            "headers": {
                "Upgrade-Insecure-Requests": "1",
                "User-Agent": "Mozilla/5.0 (Windows NT 10.0; Win64; x64) AppleWebKit/537.36 (KHTML, like Gecko) Chrome/114.0.0.0 Safari/537.36",
                "sec-ch-ua": "",
                "sec-ch-ua-mobile": "?0",
                "sec-ch-ua-platform": "\"\""
            },
            "mixedContentType": "none",
            "initialPriority": "VeryHigh",
            "referrerPolicy": "strict-origin-when-cross-origin",
            "isSameSite": true
        },
        "timestamp": 5234.889597,
        "wallTime": 1694243095.461659,
        "initiator": {
            "type": "other"
        },
        "redirectHasExtraInfo": false,
        "type": "Document",
        "frameId": "2C9B7E9893524F1533D3FB20CA355C91",
        "hasUserGesture": false,
        "cookies": {
            "cookies": []
        }
    }
]