{
    "Level 3 - Attribute Mismatch": {
        "server": {
            "content": "iwjJDxFmtdm483qSznya9hHSTkY1hUA36Oo6k2xf",
            "name": "csrf-token"
        },
        "client": {
            "content": "aJC5DxhIfpK6wulT1mJJikF0P48cVF0NFAl8ZgJk",
            "name": "csrf-token"
        }
    },
    "Level 5 - Tag Name Mismatch": {
        "server": "div",
        "client": "a"
    },
    "Level 6 - Tag Name Mismatch": {
        "server": "a",
        "client": "svg"
    },
    "Level 7 - Tag Name Mismatch": {
        "server": "div",
        "client": "path"
    }
}